erspi/__init__.py
erspi/networking.py
erspi/packet.py
erspi-0.2.0.dist-info/METADATA
erspi-0.2.0.dist-info/WHEEL
erspi-0.2.0.dist-info/license
erspi-0.2.0.dist-info/top_level.txt
erspi-0.2.0.dist-info/RECORD
