Metadata-Version: 2.2
Name: erspi
Version: 0.2.0
Summary: Enables networking between Python applications and Escape Room Software (ERS)
Author-email: dandlion <info@expandingeden.games>
Project-URL: Homepage, https://github.com/OrganicPepper/erspi
Project-URL: Issues, https://github.com/OrganicPepper/erspi/issues
Classifier: Programming Language :: Python :: 3
Classifier: License :: OSI Approved :: MIT License
Classifier: Operating System :: OS Independent
Requires-Python: >=3.8
License-File: license
Requires-Dist: paho-mqtt
